MANIFEST.in
README.md
setup.py
admin_actions/__init__.py
admin_actions/admin.py
admin_actions/static/css/admin-actions.css
admin_actions/templates/admin/change_form_object_tools.html
admin_actions/templates/admin/change_list_item_object_tools.html
admin_actions/templates/admin/change_list_object_tools.html
django_admin_actions.egg-info/PKG-INFO
django_admin_actions.egg-info/SOURCES.txt
django_admin_actions.egg-info/dependency_links.txt
django_admin_actions.egg-info/requires.txt
django_admin_actions.egg-info/top_level.txt